LICENSE
MANIFEST.in
README.rst
setup.cfg
setup.py
gimlet/__init__.py
gimlet/compat.py
gimlet/crypto.py
gimlet/factories.py
gimlet/middleware.py
gimlet/serializer.py
gimlet/session.py
gimlet/util.py
gimlet.egg-info/PKG-INFO
gimlet.egg-info/SOURCES.txt
gimlet.egg-info/dependency_links.txt
gimlet.egg-info/not-zip-safe
gimlet.egg-info/requires.txt
gimlet.egg-info/top_level.txt
gimlet/backends/__init__.py
gimlet/backends/base.py
gimlet/backends/memcache.py
gimlet/backends/pyredis.py
gimlet/backends/sql.py
gimlet/tests/__init__.py
gimlet/tests/test_backends.py
gimlet/tests/test_crypto.py
gimlet/tests/test_deferred_set.py
gimlet/tests/test_factories.py
gimlet/tests/test_middleware.py
gimlet/tests/test_session.py
gimlet/tests/test_util.py