Metadata-Version: 1.1
Name: gimlet
Version: 0.5.2
Summary: Simple High-Performance WSGI Sessions
Home-page: http://github.com/storborg/gimlet
Author: Scott Torborg
Author-email: scott@cartlogic.com
License: MIT
Keywords: wsgi sessions middleware beaker cookie
Platform: UNKNOWN
Classifier: License :: OSI Approved :: MIT License
Classifier: Programming Language :: Python :: 2
Classifier: Programming Language :: Python :: 2.7
Classifier: Programming Language :: Python :: 3
Classifier: Programming Language :: Python :: 3.3
Classifier: Programming Language :: Python :: 3.4
Classifier: Development Status :: 3 - Alpha
Classifier: Topic :: Internet :: WWW/HTTP :: WSGI :: Middleware
Classifier: Topic :: Internet :: WWW/HTTP :: Session
